odoo10_addon_l10n_fr_chorus_sale-10.0.1.0.0.99.dev11-py3.8-nspkg.pth
odoo/addons/l10n_fr_chorus_sale/README.rst
odoo/addons/l10n_fr_chorus_sale/__init__.py
odoo/addons/l10n_fr_chorus_sale/__manifest__.py
odoo/addons/l10n_fr_chorus_sale/i18n/l10n_fr_chorus_sale.pot
odoo/addons/l10n_fr_chorus_sale/models/__init__.py
odoo/addons/l10n_fr_chorus_sale/models/sale_order.py
odoo/addons/l10n_fr_chorus_sale/readme/CONTRIBUTORS.rst
odoo/addons/l10n_fr_chorus_sale/readme/DESCRIPTION.rst
odoo/addons/l10n_fr_chorus_sale/readme/USAGE.rst
odoo/addons/l10n_fr_chorus_sale/static/description/icon.png
odoo/addons/l10n_fr_chorus_sale/static/description/index.html
odoo/addons/l10n_fr_chorus_sale/views/sale_order.xml
odoo10_addon_l10n_fr_chorus_sale-10.0.1.0.0.99.dev11.dist-info/METADATA
odoo10_addon_l10n_fr_chorus_sale-10.0.1.0.0.99.dev11.dist-info/WHEEL
odoo10_addon_l10n_fr_chorus_sale-10.0.1.0.0.99.dev11.dist-info/namespace_packages.txt
odoo10_addon_l10n_fr_chorus_sale-10.0.1.0.0.99.dev11.dist-info/top_level.txt
odoo10_addon_l10n_fr_chorus_sale-10.0.1.0.0.99.dev11.dist-info/RECORD
